{"location": "Downtown, Vancouver", "data": ["{\"Category\":{\"0\":\"Public Transport\",\"1\":\"Public Transport\",\"2\":\"Public Transport\",\"3\":\"Public Transport\",\"4\":\"Public Transport\",\"5\":\"Public Transport\"},\"City\":{\"0\":\"Vancouver\",\"1\":\"Vancouver\",\"2\":\"Vancouver\",\"3\":\"Vancouver\",\"4\":\"Vancouver\",\"5\":\"Vancouver\"},\"Neighborhood\":{\"0\":\"Strathcona\",\"1\":\"Cambie Street\",\"2\":\"Cambie Street\",\"3\":\"The Village Shops\",\"4\":\"Thurlow Street\",\"5\":\"Cambie Street\"},\"Cluster Labels\":{\"0\":0,\"1\":0,\"2\":0,\"3\":0,\"4\":0,\"5\":0},\"1st Most Common Venue\":{\"0\":\"Public Transport\",\"1\":\"Public Transport\",\"2\":\"Public Transport\",\"3\":\"Public Transport\",\"4\":\"Public Transport\",\"5\":\"Public Transport\"},\"2nd Most Common Venue\":{\"0\":\"ATM\",\"1\":\"ATM\",\"2\":\"ATM\",\"3\":\"ATM\",\"4\":\"ATM\",\"5\":\"ATM\"},\"3rd Most Common Venue\":{\"0\":\"Casual Dining\",\"1\":\"Casual Dining\",\"2\":\"Casual Dining\",\"3\":\"Casual Dining\",\"4\":\"Casual Dining\",\"5\":\"Casual Dining\"},\"4th Most Common Venue\":{\"0\":\"Mall\",\"1\":\"Mall\",\"2\":\"Mall\",\"3\":\"Mall\",\"4\":\"Mall\",\"5\":\"Mall\"},\"5th Most Common Venue\":{\"0\":\"Public Transit Access\",\"1\":\"Public Transit Access\",\"2\":\"Public Transit Access\",\"3\":\"Public Transit Access\",\"4\":\"Public Transit Access\",\"5\":\"Public Transit Access\"}}", "{\"Category\":{\"0\":\"Public Transport\",\"1\":\"Public Transport\",\"2\":\"Public Transport\",\"3\":\"Public Transport\",\"4\":\"Public Transport\",\"5\":\"Public Transport\",\"6\":\"Public Transport\",\"7\":\"Public Transport\",\"8\":\"Public Transport\",\"9\":\"Public Transport\",\"10\":\"Public Transport\",\"11\":\"Public Transport\",\"12\":\"Public Transport\",\"13\":\"Public Transport\",\"14\":\"Public Transport\",\"15\":\"Public Transport\",\"16\":\"Public Transport\",\"17\":\"Public Transport\",\"18\":\"Public Transport\",\"19\":\"Supermarket\",\"20\":\"Supermarket\",\"21\":\"Supermarket\",\"22\":\"Supermarket\",\"23\":\"Supermarket\",\"24\":\"Supermarket\",\"25\":\"Supermarket\",\"26\":\"Supermarket\",\"27\":\"Supermarket\",\"28\":\"Supermarket\",\"29\":\"Supermarket\",\"30\":\"Supermarket\",\"31\":\"Supermarket\",\"32\":\"Supermarket\",\"33\":\"Supermarket\",\"34\":\"Supermarket\",\"35\":\"Supermarket\",\"36\":\"Supermarket\",\"37\":\"Supermarket\",\"38\":\"Supermarket\",\"39\":\"Supermarket\",\"40\":\"Supermarket\",\"41\":\"Supermarket\",\"42\":\"Supermarket\",\"43\":\"Supermarket\",\"44\":\"Supermarket\",\"45\":\"Supermarket\",\"46\":\"Supermarket\",\"47\":\"Supermarket\",\"48\":\"Supermarket\",\"49\":\"Supermarket\",\"50\":\"Supermarket\",\"51\":\"Supermarket\",\"52\":\"Supermarket\",\"53\":\"Supermarket\",\"54\":\"Supermarket\",\"55\":\"Mall\",\"56\":\"Mall\",\"57\":\"Mall\",\"58\":\"Mall\",\"59\":\"Mall\",\"60\":\"Mall\",\"61\":\"ATM\",\"62\":\"ATM\",\"63\":\"ATM\",\"64\":\"ATM\",\"65\":\"ATM\",\"66\":\"ATM\",\"67\":\"ATM\",\"68\":\"ATM\",\"69\":\"ATM\",\"70\":\"ATM\",\"71\":\"ATM\",\"72\":\"ATM\",\"73\":\"ATM\",\"74\":\"ATM\",\"75\":\"ATM\",\"76\":\"ATM\",\"77\":\"ATM\",\"78\":\"ATM\",\"79\":\"ATM\",\"80\":\"ATM\",\"81\":\"ATM\",\"82\":\"ATM\",\"83\":\"ATM\",\"84\":\"ATM\",\"85\":\"ATM\",\"86\":\"ATM\",\"87\":\"ATM\",\"88\":\"ATM\",\"89\":\"ATM\",\"90\":\"ATM\",\"91\":\"ATM\",\"92\":\"ATM\",\"93\":\"ATM\"},\"City\":{\"0\":\"Vancouver\",\"1\":\"Vancouver\",\"2\":\"Vancouver\",\"3\":\"Vancouver\",\"4\":\"Vancouver\",\"5\":\"Vancouver\",\"6\":\"Vancouver\",\"7\":\"Vancouver\",\"8\":\"Vancouver\",\"9\":\"Vancouver\",\"10\":\"Vancouver\",\"11\":\"Vancouver\",\"12\":\"Vancouver\",\"13\":\"Vancouver\",\"14\":\"Vancouver\",\"15\":\"Vancouver\",\"16\":\"Vancouver\",\"17\":\"Vancouver\",\"18\":\"Vancouver\",\"19\":\"Vancouver\",\"20\":\"Vancouver\",\"21\":\"Vancouver\",\"22\":\"Vancouver\",\"23\":\"Vancouver\",\"24\":\"Vancouver\",\"25\":\"Vancouver\",\"26\":\"Vancouver\",\"27\":\"Vancouver\",\"28\":\"Vancouver\",\"29\":\"Vancouver\",\"30\":\"Vancouver\",\"31\":\"Vancouver\",\"32\":\"Vancouver\",\"33\":\"Vancouver\",\"34\":\"Vancouver\",\"35\":\"Vancouver\",\"36\":\"Vancouver\",\"37\":\"Vancouver\",\"38\":\"Vancouver\",\"39\":\"Vancouver\",\"40\":\"Vancouver\",\"41\":\"Vancouver\",\"42\":\"Vancouver\",\"43\":\"Vancouver\",\"44\":\"Vancouver\",\"45\":\"Vancouver\",\"46\":\"Vancouver\",\"47\":\"Vancouver\",\"48\":\"Vancouver\",\"49\":\"Vancouver\",\"50\":\"Vancouver\",\"51\":\"Vancouver\",\"52\":\"Vancouver\",\"53\":\"Vancouver\",\"54\":\"Vancouver\",\"55\":\"Vancouver\",\"56\":\"Vancouver\",\"57\":\"Vancouver\",\"58\":\"Vancouver\",\"59\":\"Vancouver\",\"60\":\"Vancouver\",\"61\":\"Vancouver\",\"62\":\"Vancouver\",\"63\":\"Vancouver\",\"64\":\"Vancouver\",\"65\":\"Vancouver\",\"66\":\"Vancouver\",\"67\":\"Vancouver\",\"68\":\"Vancouver\",\"69\":\"Vancouver\",\"70\":\"Vancouver\",\"71\":\"Vancouver\",\"72\":\"Vancouver\",\"73\":\"Vancouver\",\"74\":\"Vancouver\",\"75\":\"Vancouver\",\"76\":\"Vancouver\",\"77\":\"Vancouver\",\"78\":\"Vancouver\",\"79\":\"Vancouver\",\"80\":\"Vancouver\",\"81\":\"Vancouver\",\"82\":\"Vancouver\",\"83\":\"Vancouver\",\"84\":\"Vancouver\",\"85\":\"Vancouver\",\"86\":\"Vancouver\",\"87\":\"Vancouver\",\"88\":\"Vancouver\",\"89\":\"Vancouver\",\"90\":\"Vancouver\",\"91\":\"Vancouver\",\"92\":\"Vancouver\",\"93\":\"Vancouver\"},\"Neighborhood\":{\"0\":\"West Georgia Street\",\"1\":\"West Georgia Street\",\"2\":\"Seymour Street\",\"3\":\"West Georgia Street\",\"4\":\"St. Regis Lane\",\"5\":\"Seymour Street\",\"6\":\"Yaletown\",\"7\":\"West Georgia Street\",\"8\":\"Seymour Street\",\"9\":\"Robson Street\",\"10\":\"Yaletown\",\"11\":\"Yaletown\",\"12\":\"Robson Street\",\"13\":\"Nelson Street\",\"14\":\"Yaletown\",\"15\":\"Yaletown\",\"16\":\"Yaletown\",\"17\":\"Yaletown\",\"18\":\"Yaletown\",\"19\":\"Seymour Street\",\"20\":\"Seymour Street\",\"21\":\"Dunsmuir Street\",\"22\":\"Seymour Street\",\"23\":\"Seymour Street\",\"24\":\"Homer Street\",\"25\":\"St. Regis Lane\",\"26\":\"Yaletown\",\"27\":\"West Georgia Street\",\"28\":\"West Georgia Street\",\"29\":\"Seymour Street\",\"30\":\"Seymour Street\",\"31\":\"Yaletown\",\"32\":\"Yaletown\",\"33\":\"Robson Street\",\"34\":\"Seymour Street\",\"35\":\"Seymour Street\",\"36\":\"Yaletown\",\"37\":\"Yaletown\",\"38\":\"Yaletown\",\"39\":\"Yaletown\",\"40\":\"West Cordova Street\",\"41\":\"Nelson Street\",\"42\":\"West Georgia Street\",\"43\":\"Yaletown\",\"44\":\"Robson Street\",\"45\":\"Yaletown\",\"46\":\"Yaletown\",\"47\":\"Mainland Street\",\"48\":\"Pacific Boulevard\",\"49\":\"Yaletown\",\"50\":\"West Cordova Street\",\"51\":\"Yaletown\",\"52\":\"Yaletown\",\"53\":\"Davie Street\",\"54\":\"Yaletown\",\"55\":\"West Georgia Street\",\"56\":\"West Georgia Street\",\"57\":\"Yaletown\",\"58\":\"Robson Street\",\"59\":\"Homer Street\",\"60\":\"Dunsmuir Street\",\"61\":\"West Georgia Street\",\"62\":\"Seymour Street\",\"63\":\"Seymour Street\",\"64\":\"Seymour Street\",\"65\":\"St. Regis Lane\",\"66\":\"Yaletown\",\"67\":\"West Georgia Street\",\"68\":\"Yaletown\",\"69\":\"Yaletown\",\"70\":\"Yaletown\",\"71\":\"Yaletown\",\"72\":\"Seymour Street\",\"73\":\"Yaletown\",\"74\":\"Yaletown\",\"75\":\"Yaletown\",\"76\":\"Mainland Street\",\"77\":\"Robson Street\",\"78\":\"West Cordova Street\",\"79\":\"West Georgia Street\",\"80\":\"West Georgia Street\",\"81\":\"Homer Street\",\"82\":\"West Georgia Street\",\"83\":\"Yaletown\",\"84\":\"Nelson Street\",\"85\":\"Yaletown\",\"86\":\"Dunsmuir Street\",\"87\":\"Yaletown\",\"88\":\"Pacific Boulevard\",\"89\":\"Pacific Boulevard\",\"90\":\"Yaletown\",\"91\":\"Davie Street\",\"92\":\"Robson Street\",\"93\":\"Davie Street\"},\"Cluster Labels\":{\"0\":1,\"1\":1,\"2\":1,\"3\":1,\"4\":1,\"5\":1,\"6\":1,\"7\":1,\"8\":1,\"9\":1,\"10\":1,\"11\":1,\"12\":1,\"13\":1,\"14\":1,\"15\":1,\"16\":1,\"17\":1,\"18\":1,\"19\":1,\"20\":1,\"21\":1,\"22\":1,\"23\":1,\"24\":1,\"25\":1,\"26\":1,\"27\":1,\"28\":1,\"29\":1,\"30\":1,\"31\":1,\"32\":1,\"33\":1,\"34\":1,\"35\":1,\"36\":1,\"37\":1,\"38\":1,\"39\":1,\"40\":1,\"41\":1,\"42\":1,\"43\":1,\"44\":1,\"45\":1,\"46\":1,\"47\":1,\"48\":1,\"49\":1,\"50\":1,\"51\":1,\"52\":1,\"53\":1,\"54\":1,\"55\":1,\"56\":1,\"57\":1,\"58\":1,\"59\":1,\"60\":1,\"61\":1,\"62\":1,\"63\":1,\"64\":1,\"65\":1,\"66\":1,\"67\":1,\"68\":1,\"69\":1,\"70\":1,\"71\":1,\"72\":1,\"73\":1,\"74\":1,\"75\":1,\"76\":1,\"77\":1,\"78\":1,\"79\":1,\"80\":1,\"81\":1,\"82\":1,\"83\":1,\"84\":1,\"85\":1,\"86\":1,\"87\":1,\"88\":1,\"89\":1,\"90\":1,\"91\":1,\"92\":1,\"93\":1},\"1st Most Common Venue\":{\"0\":\"ATM\",\"1\":\"ATM\",\"2\":\"Supermarket\",\"3\":\"ATM\",\"4\":\"ATM\",\"5\":\"Supermarket\",\"6\":\"Supermarket\",\"7\":\"ATM\",\"8\":\"Supermarket\",\"9\":\"ATM\",\"10\":\"Supermarket\",\"11\":\"Supermarket\",\"12\":\"ATM\",\"13\":\"ATM\",\"14\":\"Supermarket\",\"15\":\"Supermarket\",\"16\":\"Supermarket\",\"17\":\"Supermarket\",\"18\":\"Supermarket\",\"19\":\"Supermarket\",\"20\":\"Supermarket\",\"21\":\"ATM\",\"22\":\"Supermarket\",\"23\":\"Supermarket\",\"24\":\"ATM\",\"25\":\"ATM\",\"26\":\"Supermarket\",\"27\":\"ATM\",\"28\":\"ATM\",\"29\":\"Supermarket\",\"30\":\"Supermarket\",\"31\":\"Supermarket\",\"32\":\"Supermarket\",\"33\":\"ATM\",\"34\":\"Supermarket\",\"35\":\"Supermarket\",\"36\":\"Supermarket\",\"37\":\"Supermarket\",\"38\":\"Supermarket\",\"39\":\"Supermarket\",\"40\":\"Supermarket\",\"41\":\"ATM\",\"42\":\"ATM\",\"43\":\"Supermarket\",\"44\":\"ATM\",\"45\":\"Supermarket\",\"46\":\"Supermarket\",\"47\":\"ATM\",\"48\":\"ATM\",\"49\":\"Supermarket\",\"50\":\"Supermarket\",\"51\":\"Supermarket\",\"52\":\"Supermarket\",\"53\":\"ATM\",\"54\":\"Supermarket\",\"55\":\"ATM\",\"56\":\"ATM\",\"57\":\"Supermarket\",\"58\":\"ATM\",\"59\":\"ATM\",\"60\":\"ATM\",\"61\":\"ATM\",\"62\":\"Supermarket\",\"63\":\"Supermarket\",\"64\":\"Supermarket\",\"65\":\"ATM\",\"66\":\"Supermarket\",\"67\":\"ATM\",\"68\":\"Supermarket\",\"69\":\"Supermarket\",\"70\":\"Supermarket\",\"71\":\"Supermarket\",\"72\":\"Supermarket\",\"73\":\"Supermarket\",\"74\":\"Supermarket\",\"75\":\"Supermarket\",\"76\":\"ATM\",\"77\":\"ATM\",\"78\":\"Supermarket\",\"79\":\"ATM\",\"80\":\"ATM\",\"81\":\"ATM\",\"82\":\"ATM\",\"83\":\"Supermarket\",\"84\":\"ATM\",\"85\":\"Supermarket\",\"86\":\"ATM\",\"87\":\"Supermarket\",\"88\":\"ATM\",\"89\":\"ATM\",\"90\":\"Supermarket\",\"91\":\"ATM\",\"92\":\"ATM\",\"93\":\"ATM\"},\"2nd Most Common Venue\":{\"0\":\"Public Transport\",\"1\":\"Public Transport\",\"2\":\"ATM\",\"3\":\"Public Transport\",\"4\":\"Public Transport\",\"5\":\"ATM\",\"6\":\"ATM\",\"7\":\"Public Transport\",\"8\":\"ATM\",\"9\":\"Public Transport\",\"10\":\"ATM\",\"11\":\"ATM\",\"12\":\"Public Transport\",\"13\":\"Public Transport\",\"14\":\"ATM\",\"15\":\"ATM\",\"16\":\"ATM\",\"17\":\"ATM\",\"18\":\"ATM\",\"19\":\"ATM\",\"20\":\"ATM\",\"21\":\"Mall\",\"22\":\"ATM\",\"23\":\"ATM\",\"24\":\"Mall\",\"25\":\"Public Transport\",\"26\":\"ATM\",\"27\":\"Public Transport\",\"28\":\"Public Transport\",\"29\":\"ATM\",\"30\":\"ATM\",\"31\":\"ATM\",\"32\":\"ATM\",\"33\":\"Public Transport\",\"34\":\"ATM\",\"35\":\"ATM\",\"36\":\"ATM\",\"37\":\"ATM\",\"38\":\"ATM\",\"39\":\"ATM\",\"40\":\"ATM\",\"41\":\"Public Transport\",\"42\":\"Public Transport\",\"43\":\"ATM\",\"44\":\"Public Transport\",\"45\":\"ATM\",\"46\":\"ATM\",\"47\":\"Supermarket\",\"48\":\"Supermarket\",\"49\":\"ATM\",\"50\":\"ATM\",\"51\":\"ATM\",\"52\":\"ATM\",\"53\":\"Supermarket\",\"54\":\"ATM\",\"55\":\"Public Transport\",\"56\":\"Public Transport\",\"57\":\"ATM\",\"58\":\"Public Transport\",\"59\":\"Mall\",\"60\":\"Mall\",\"61\":\"Public Transport\",\"62\":\"ATM\",\"63\":\"ATM\",\"64\":\"ATM\",\"65\":\"Public Transport\",\"66\":\"ATM\",\"67\":\"Public Transport\",\"68\":\"ATM\",\"69\":\"ATM\",\"70\":\"ATM\",\"71\":\"ATM\",\"72\":\"ATM\",\"73\":\"ATM\",\"74\":\"ATM\",\"75\":\"ATM\",\"76\":\"Supermarket\",\"77\":\"Public Transport\",\"78\":\"ATM\",\"79\":\"Public Transport\",\"80\":\"Public Transport\",\"81\":\"Mall\",\"82\":\"Public Transport\",\"83\":\"ATM\",\"84\":\"Public Transport\",\"85\":\"ATM\",\"86\":\"Mall\",\"87\":\"ATM\",\"88\":\"Supermarket\",\"89\":\"Supermarket\",\"90\":\"ATM\",\"91\":\"Supermarket\",\"92\":\"Public Transport\",\"93\":\"Supermarket\"},\"3rd Most Common Venue\":{\"0\":\"Supermarket\",\"1\":\"Supermarket\",\"2\":\"Public Transport\",\"3\":\"Supermarket\",\"4\":\"Supermarket\",\"5\":\"Public Transport\",\"6\":\"Public Transport\",\"7\":\"Supermarket\",\"8\":\"Public Transport\",\"9\":\"Supermarket\",\"10\":\"Public Transport\",\"11\":\"Public Transport\",\"12\":\"Supermarket\",\"13\":\"Supermarket\",\"14\":\"Public Transport\",\"15\":\"Public Transport\",\"16\":\"Public Transport\",\"17\":\"Public Transport\",\"18\":\"Public Transport\",\"19\":\"Public Transport\",\"20\":\"Public Transport\",\"21\":\"Supermarket\",\"22\":\"Public Transport\",\"23\":\"Public Transport\",\"24\":\"Supermarket\",\"25\":\"Supermarket\",\"26\":\"Public Transport\",\"27\":\"Supermarket\",\"28\":\"Supermarket\",\"29\":\"Public Transport\",\"30\":\"Public Transport\",\"31\":\"Public Transport\",\"32\":\"Public Transport\",\"33\":\"Supermarket\",\"34\":\"Public Transport\",\"35\":\"Public Transport\",\"36\":\"Public Transport\",\"37\":\"Public Transport\",\"38\":\"Public Transport\",\"39\":\"Public Transport\",\"40\":\"Casual Dining\",\"41\":\"Supermarket\",\"42\":\"Supermarket\",\"43\":\"Public Transport\",\"44\":\"Supermarket\",\"45\":\"Public Transport\",\"46\":\"Public Transport\",\"47\":\"Casual Dining\",\"48\":\"Casual Dining\",\"49\":\"Public Transport\",\"50\":\"Casual Dining\",\"51\":\"Public Transport\",\"52\":\"Public Transport\",\"53\":\"Casual Dining\",\"54\":\"Public Transport\",\"55\":\"Supermarket\",\"56\":\"Supermarket\",\"57\":\"Public Transport\",\"58\":\"Supermarket\",\"59\":\"Supermarket\",\"60\":\"Supermarket\",\"61\":\"Supermarket\",\"62\":\"Public Transport\",\"63\":\"Public Transport\",\"64\":\"Public Transport\",\"65\":\"Supermarket\",\"66\":\"Public Transport\",\"67\":\"Supermarket\",\"68\":\"Public Transport\",\"69\":\"Public Transport\",\"70\":\"Public Transport\",\"71\":\"Public Transport\",\"72\":\"Public Transport\",\"73\":\"Public Transport\",\"74\":\"Public Transport\",\"75\":\"Public Transport\",\"76\":\"Casual Dining\",\"77\":\"Supermarket\",\"78\":\"Casual Dining\",\"79\":\"Supermarket\",\"80\":\"Supermarket\",\"81\":\"Supermarket\",\"82\":\"Supermarket\",\"83\":\"Public Transport\",\"84\":\"Supermarket\",\"85\":\"Public Transport\",\"86\":\"Supermarket\",\"87\":\"Public Transport\",\"88\":\"Casual Dining\",\"89\":\"Casual Dining\",\"90\":\"Public Transport\",\"91\":\"Casual Dining\",\"92\":\"Supermarket\",\"93\":\"Casual Dining\"},\"4th Most Common Venue\":{\"0\":\"Mall\",\"1\":\"Mall\",\"2\":\"Casual Dining\",\"3\":\"Mall\",\"4\":\"Casual Dining\",\"5\":\"Casual Dining\",\"6\":\"Mall\",\"7\":\"Mall\",\"8\":\"Casual Dining\",\"9\":\"Mall\",\"10\":\"Mall\",\"11\":\"Mall\",\"12\":\"Mall\",\"13\":\"Casual Dining\",\"14\":\"Mall\",\"15\":\"Mall\",\"16\":\"Mall\",\"17\":\"Mall\",\"18\":\"Mall\",\"19\":\"Casual Dining\",\"20\":\"Casual Dining\",\"21\":\"Casual Dining\",\"22\":\"Casual Dining\",\"23\":\"Casual Dining\",\"24\":\"Casual Dining\",\"25\":\"Casual Dining\",\"26\":\"Mall\",\"27\":\"Mall\",\"28\":\"Mall\",\"29\":\"Casual Dining\",\"30\":\"Casual Dining\",\"31\":\"Mall\",\"32\":\"Mall\",\"33\":\"Mall\",\"34\":\"Casual Dining\",\"35\":\"Casual Dining\",\"36\":\"Mall\",\"37\":\"Mall\",\"38\":\"Mall\",\"39\":\"Mall\",\"40\":\"Mall\",\"41\":\"Casual Dining\",\"42\":\"Mall\",\"43\":\"Mall\",\"44\":\"Mall\",\"45\":\"Mall\",\"46\":\"Mall\",\"47\":\"Mall\",\"48\":\"Mall\",\"49\":\"Mall\",\"50\":\"Mall\",\"51\":\"Mall\",\"52\":\"Mall\",\"53\":\"Mall\",\"54\":\"Mall\",\"55\":\"Mall\",\"56\":\"Mall\",\"57\":\"Mall\",\"58\":\"Mall\",\"59\":\"Casual Dining\",\"60\":\"Casual Dining\",\"61\":\"Mall\",\"62\":\"Casual Dining\",\"63\":\"Casual Dining\",\"64\":\"Casual Dining\",\"65\":\"Casual Dining\",\"66\":\"Mall\",\"67\":\"Mall\",\"68\":\"Mall\",\"69\":\"Mall\",\"70\":\"Mall\",\"71\":\"Mall\",\"72\":\"Casual Dining\",\"73\":\"Mall\",\"74\":\"Mall\",\"75\":\"Mall\",\"76\":\"Mall\",\"77\":\"Mall\",\"78\":\"Mall\",\"79\":\"Mall\",\"80\":\"Mall\",\"81\":\"Casual Dining\",\"82\":\"Mall\",\"83\":\"Mall\",\"84\":\"Casual Dining\",\"85\":\"Mall\",\"86\":\"Casual Dining\",\"87\":\"Mall\",\"88\":\"Mall\",\"89\":\"Mall\",\"90\":\"Mall\",\"91\":\"Mall\",\"92\":\"Mall\",\"93\":\"Mall\"},\"5th Most Common Venue\":{\"0\":\"Casual Dining\",\"1\":\"Casual Dining\",\"2\":\"Mall\",\"3\":\"Casual Dining\",\"4\":\"Mall\",\"5\":\"Mall\",\"6\":\"Casual Dining\",\"7\":\"Casual Dining\",\"8\":\"Mall\",\"9\":\"Casual Dining\",\"10\":\"Casual Dining\",\"11\":\"Casual Dining\",\"12\":\"Casual Dining\",\"13\":\"Mall\",\"14\":\"Casual Dining\",\"15\":\"Casual Dining\",\"16\":\"Casual Dining\",\"17\":\"Casual Dining\",\"18\":\"Casual Dining\",\"19\":\"Mall\",\"20\":\"Mall\",\"21\":\"Public Transit Access\",\"22\":\"Mall\",\"23\":\"Mall\",\"24\":\"Public Transit Access\",\"25\":\"Mall\",\"26\":\"Casual Dining\",\"27\":\"Casual Dining\",\"28\":\"Casual Dining\",\"29\":\"Mall\",\"30\":\"Mall\",\"31\":\"Casual Dining\",\"32\":\"Casual Dining\",\"33\":\"Casual Dining\",\"34\":\"Mall\",\"35\":\"Mall\",\"36\":\"Casual Dining\",\"37\":\"Casual Dining\",\"38\":\"Casual Dining\",\"39\":\"Casual Dining\",\"40\":\"Public Transit Access\",\"41\":\"Mall\",\"42\":\"Casual Dining\",\"43\":\"Casual Dining\",\"44\":\"Casual Dining\",\"45\":\"Casual Dining\",\"46\":\"Casual Dining\",\"47\":\"Public Transit Access\",\"48\":\"Public Transit Access\",\"49\":\"Casual Dining\",\"50\":\"Public Transit Access\",\"51\":\"Casual Dining\",\"52\":\"Casual Dining\",\"53\":\"Public Transit Access\",\"54\":\"Casual Dining\",\"55\":\"Casual Dining\",\"56\":\"Casual Dining\",\"57\":\"Casual Dining\",\"58\":\"Casual Dining\",\"59\":\"Public Transit Access\",\"60\":\"Public Transit Access\",\"61\":\"Casual Dining\",\"62\":\"Mall\",\"63\":\"Mall\",\"64\":\"Mall\",\"65\":\"Mall\",\"66\":\"Casual Dining\",\"67\":\"Casual Dining\",\"68\":\"Casual Dining\",\"69\":\"Casual Dining\",\"70\":\"Casual Dining\",\"71\":\"Casual Dining\",\"72\":\"Mall\",\"73\":\"Casual Dining\",\"74\":\"Casual Dining\",\"75\":\"Casual Dining\",\"76\":\"Public Transit Access\",\"77\":\"Casual Dining\",\"78\":\"Public Transit Access\",\"79\":\"Casual Dining\",\"80\":\"Casual Dining\",\"81\":\"Public Transit Access\",\"82\":\"Casual Dining\",\"83\":\"Casual Dining\",\"84\":\"Mall\",\"85\":\"Casual Dining\",\"86\":\"Public Transit Access\",\"87\":\"Casual Dining\",\"88\":\"Public Transit Access\",\"89\":\"Public Transit Access\",\"90\":\"Casual Dining\",\"91\":\"Public Transit Access\",\"92\":\"Casual Dining\",\"93\":\"Public Transit Access\"}}", "{\"Category\":{\"0\":\"Public Transport\",\"1\":\"Public Transport\",\"2\":\"Public Transport\",\"3\":\"Public Transport\",\"4\":\"Public Transport\",\"5\":\"Public Transport\",\"6\":\"Public Transport\",\"7\":\"Public Transport\",\"8\":\"Public Transport\",\"9\":\"Public Transport\",\"10\":\"Public Transport\",\"11\":\"Public Transport\",\"12\":\"Public Transport\",\"13\":\"Public Transport\",\"14\":\"Public Transport\",\"15\":\"Public Transport\",\"16\":\"Public Transport\",\"17\":\"Public Transport\",\"18\":\"Public Transit Access\",\"19\":\"Public Transport\",\"20\":\"Public Transport\",\"21\":\"Public Transport\",\"22\":\"Public Transport\",\"23\":\"Public Transport\",\"24\":\"Public Transport\",\"25\":\"Public Transit Access\",\"26\":\"Public Transport\",\"27\":\"Public Transport\",\"28\":\"Public Transit Access\",\"29\":\"Public Transport\",\"30\":\"Public Transport\",\"31\":\"Public Transport\",\"32\":\"Public Transport\",\"33\":\"Public Transport\",\"34\":\"Public Transport\",\"35\":\"Public Transport\",\"36\":\"Public Transport\",\"37\":\"Public Transit Access\",\"38\":\"Supermarket\",\"39\":\"Supermarket\",\"40\":\"Supermarket\",\"41\":\"Supermarket\",\"42\":\"Supermarket\",\"43\":\"Supermarket\",\"44\":\"Supermarket\",\"45\":\"Supermarket\",\"46\":\"Supermarket\",\"47\":\"Mall\",\"48\":\"Mall\",\"49\":\"Mall\",\"50\":\"Mall\",\"51\":\"Mall\",\"52\":\"ATM\",\"53\":\"ATM\",\"54\":\"ATM\",\"55\":\"ATM\",\"56\":\"ATM\",\"57\":\"ATM\",\"58\":\"ATM\",\"59\":\"ATM\",\"60\":\"ATM\",\"61\":\"ATM\",\"62\":\"ATM\",\"63\":\"ATM\",\"64\":\"ATM\",\"65\":\"ATM\",\"66\":\"ATM\",\"67\":\"ATM\",\"68\":\"ATM\",\"69\":\"ATM\",\"70\":\"ATM\",\"71\":\"ATM\",\"72\":\"ATM\",\"73\":\"ATM\",\"74\":\"ATM\",\"75\":\"ATM\",\"76\":\"ATM\",\"77\":\"ATM\",\"78\":\"ATM\",\"79\":\"ATM\",\"80\":\"ATM\",\"81\":\"ATM\",\"82\":\"ATM\",\"83\":\"ATM\",\"84\":\"ATM\",\"85\":\"ATM\",\"86\":\"ATM\",\"87\":\"ATM\",\"88\":\"ATM\",\"89\":\"ATM\",\"90\":\"ATM\",\"91\":\"ATM\"},\"City\":{\"0\":\"Vancouver\",\"1\":\"Vancouver\",\"2\":\"Vancouver\",\"3\":\"Vancouver\",\"4\":\"Vancouver\",\"5\":\"Vancouver\",\"6\":\"Vancouver\",\"7\":\"Vancouver\",\"8\":\"Vancouver\",\"9\":\"Vancouver\",\"10\":\"Vancouver\",\"11\":\"Vancouver\",\"12\":\"Vancouver\",\"13\":\"Vancouver\",\"14\":\"Vancouver\",\"15\":\"Vancouver\",\"16\":\"Vancouver\",\"17\":\"Vancouver\",\"18\":\"Vancouver\",\"19\":\"Vancouver\",\"20\":\"Vancouver\",\"21\":\"Vancouver\",\"22\":\"Vancouver\",\"23\":\"Vancouver\",\"24\":\"Vancouver\",\"25\":\"Vancouver\",\"26\":\"Vancouver\",\"27\":\"Vancouver\",\"28\":\"Vancouver\",\"29\":\"Vancouver\",\"30\":\"Vancouver\",\"31\":\"Vancouver\",\"32\":\"Vancouver\",\"33\":\"Vancouver\",\"34\":\"Vancouver\",\"35\":\"Vancouver\",\"36\":\"Vancouver\",\"37\":\"Vancouver\",\"38\":\"Vancouver\",\"39\":\"Vancouver\",\"40\":\"Vancouver\",\"41\":\"Vancouver\",\"42\":\"Vancouver\",\"43\":\"Vancouver\",\"44\":\"Vancouver\",\"45\":\"Vancouver\",\"46\":\"Vancouver\",\"47\":\"Vancouver\",\"48\":\"Vancouver\",\"49\":\"Vancouver\",\"50\":\"Vancouver\",\"51\":\"Vancouver\",\"52\":\"Vancouver\",\"53\":\"Vancouver\",\"54\":\"Vancouver\",\"55\":\"Vancouver\",\"56\":\"Vancouver\",\"57\":\"Vancouver\",\"58\":\"Vancouver\",\"59\":\"Vancouver\",\"60\":\"Vancouver\",\"61\":\"Vancouver\",\"62\":\"Vancouver\",\"63\":\"Vancouver\",\"64\":\"Vancouver\",\"65\":\"Vancouver\",\"66\":\"Vancouver\",\"67\":\"Vancouver\",\"68\":\"Vancouver\",\"69\":\"Vancouver\",\"70\":\"Vancouver\",\"71\":\"Vancouver\",\"72\":\"Vancouver\",\"73\":\"Vancouver\",\"74\":\"Vancouver\",\"75\":\"Vancouver\",\"76\":\"Vancouver\",\"77\":\"Vancouver\",\"78\":\"Vancouver\",\"79\":\"Vancouver\",\"80\":\"Vancouver\",\"81\":\"Vancouver\",\"82\":\"Vancouver\",\"83\":\"Vancouver\",\"84\":\"Vancouver\",\"85\":\"Vancouver\",\"86\":\"Vancouver\",\"87\":\"Vancouver\",\"88\":\"Vancouver\",\"89\":\"Vancouver\",\"90\":\"Vancouver\",\"91\":\"Vancouver\"},\"Neighborhood\":{\"0\":\"Downtown\",\"1\":\"Downtown\",\"2\":\"Downtown\",\"3\":\"Downtown\",\"4\":\"Downtown\",\"5\":\"Downtown\",\"6\":\"Downtown\",\"7\":\"Downtown\",\"8\":\"Downtown\",\"9\":\"West Pender Street\",\"10\":\"Downtown\",\"11\":\"Downtown\",\"12\":\"West Pender Street\",\"13\":\"Downtown\",\"14\":\"West Pender Street\",\"15\":\"Downtown\",\"16\":\"West Pender Street\",\"17\":\"West Pender Street\",\"18\":\"West Pender Street\",\"19\":\"Downtown\",\"20\":\"Downtown\",\"21\":\"Downtown\",\"22\":\"Downtown\",\"23\":\"Burrard Street\",\"24\":\"Beatty Street\",\"25\":\"Downtown\",\"26\":\"Downtown\",\"27\":\"Downtown\",\"28\":\"Vancouver\",\"29\":\"Downtown\",\"30\":\"Downtown\",\"31\":\"Downtown\",\"32\":\"Downtown\",\"33\":\"Burrard Street\",\"34\":\"Vancouver\",\"35\":\"Downtown\",\"36\":\"West Pender Street\",\"37\":\"Burrard Street\",\"38\":\"Downtown\",\"39\":\"Downtown\",\"40\":\"Burrard Street\",\"41\":\"Burrard Street\",\"42\":\"West Pender Street\",\"43\":\"Burrard Street\",\"44\":\"Downtown\",\"45\":\"Downtown\",\"46\":\"Downtown\",\"47\":\"Downtown\",\"48\":\"Downtown\",\"49\":\"Downtown\",\"50\":\"West Pender Street\",\"51\":\"Downtown\",\"52\":\"Downtown\",\"53\":\"Downtown\",\"54\":\"Downtown\",\"55\":\"Downtown\",\"56\":\"Downtown\",\"57\":\"Downtown\",\"58\":\"Downtown\",\"59\":\"Downtown\",\"60\":\"West Pender Street\",\"61\":\"West Pender Street\",\"62\":\"Downtown\",\"63\":\"Downtown\",\"64\":\"West Pender Street\",\"65\":\"Downtown\",\"66\":\"Downtown\",\"67\":\"Beatty Street\",\"68\":\"Beatty Street\",\"69\":\"Downtown\",\"70\":\"Burrard Street\",\"71\":\"Burrard Street\",\"72\":\"Burrard Street\",\"73\":\"Downtown\",\"74\":\"Burrard Street\",\"75\":\"Downtown\",\"76\":\"Vancouver\",\"77\":\"Downtown\",\"78\":\"Downtown\",\"79\":\"Downtown\",\"80\":\"West Pender Street\",\"81\":\"Burrard Street\",\"82\":\"Burrard Street\",\"83\":\"West Pender Street\",\"84\":\"West Pender Street\",\"85\":\"Downtown\",\"86\":\"Burrard Street\",\"87\":\"Downtown\",\"88\":\"Downtown\",\"89\":\"Vancouver\",\"90\":\"Downtown\",\"91\":\"Marinaside Crescent\"},\"Cluster Labels\":{\"0\":2,\"1\":2,\"2\":2,\"3\":2,\"4\":2,\"5\":2,\"6\":2,\"7\":2,\"8\":2,\"9\":2,\"10\":2,\"11\":2,\"12\":2,\"13\":2,\"14\":2,\"15\":2,\"16\":2,\"17\":2,\"18\":2,\"19\":2,\"20\":2,\"21\":2,\"22\":2,\"23\":2,\"24\":2,\"25\":2,\"26\":2,\"27\":2,\"28\":2,\"29\":2,\"30\":2,\"31\":2,\"32\":2,\"33\":2,\"34\":2,\"35\":2,\"36\":2,\"37\":2,\"38\":2,\"39\":2,\"40\":2,\"41\":2,\"42\":2,\"43\":2,\"44\":2,\"45\":2,\"46\":2,\"47\":2,\"48\":2,\"49\":2,\"50\":2,\"51\":2,\"52\":2,\"53\":2,\"54\":2,\"55\":2,\"56\":2,\"57\":2,\"58\":2,\"59\":2,\"60\":2,\"61\":2,\"62\":2,\"63\":2,\"64\":2,\"65\":2,\"66\":2,\"67\":2,\"68\":2,\"69\":2,\"70\":2,\"71\":2,\"72\":2,\"73\":2,\"74\":2,\"75\":2,\"76\":2,\"77\":2,\"78\":2,\"79\":2,\"80\":2,\"81\":2,\"82\":2,\"83\":2,\"84\":2,\"85\":2,\"86\":2,\"87\":2,\"88\":2,\"89\":2,\"90\":2,\"91\":2},\"1st Most Common Venue\":{\"0\":\"Public Transport\",\"1\":\"Public Transport\",\"2\":\"Public Transport\",\"3\":\"Public Transport\",\"4\":\"Public Transport\",\"5\":\"Public Transport\",\"6\":\"Public Transport\",\"7\":\"Public Transport\",\"8\":\"Public Transport\",\"9\":\"ATM\",\"10\":\"Public Transport\",\"11\":\"Public Transport\",\"12\":\"ATM\",\"13\":\"Public Transport\",\"14\":\"ATM\",\"15\":\"Public Transport\",\"16\":\"ATM\",\"17\":\"ATM\",\"18\":\"ATM\",\"19\":\"Public Transport\",\"20\":\"Public Transport\",\"21\":\"Public Transport\",\"22\":\"Public Transport\",\"23\":\"ATM\",\"24\":\"ATM\",\"25\":\"Public Transport\",\"26\":\"Public Transport\",\"27\":\"Public Transport\",\"28\":\"ATM\",\"29\":\"Public Transport\",\"30\":\"Public Transport\",\"31\":\"Public Transport\",\"32\":\"Public Transport\",\"33\":\"ATM\",\"34\":\"ATM\",\"35\":\"Public Transport\",\"36\":\"ATM\",\"37\":\"ATM\",\"38\":\"Public Transport\",\"39\":\"Public Transport\",\"40\":\"ATM\",\"41\":\"ATM\",\"42\":\"ATM\",\"43\":\"ATM\",\"44\":\"Public Transport\",\"45\":\"Public Transport\",\"46\":\"Public Transport\",\"47\":\"Public Transport\",\"48\":\"Public Transport\",\"49\":\"Public Transport\",\"50\":\"ATM\",\"51\":\"Public Transport\",\"52\":\"Public Transport\",\"53\":\"Public Transport\",\"54\":\"Public Transport\",\"55\":\"Public Transport\",\"56\":\"Public Transport\",\"57\":\"Public Transport\",\"58\":\"Public Transport\",\"59\":\"Public Transport\",\"60\":\"ATM\",\"61\":\"ATM\",\"62\":\"Public Transport\",\"63\":\"Public Transport\",\"64\":\"ATM\",\"65\":\"Public Transport\",\"66\":\"Public Transport\",\"67\":\"ATM\",\"68\":\"ATM\",\"69\":\"Public Transport\",\"70\":\"ATM\",\"71\":\"ATM\",\"72\":\"ATM\",\"73\":\"Public Transport\",\"74\":\"ATM\",\"75\":\"Public Transport\",\"76\":\"ATM\",\"77\":\"Public Transport\",\"78\":\"Public Transport\",\"79\":\"Public Transport\",\"80\":\"ATM\",\"81\":\"ATM\",\"82\":\"ATM\",\"83\":\"ATM\",\"84\":\"ATM\",\"85\":\"Public Transport\",\"86\":\"ATM\",\"87\":\"Public Transport\",\"88\":\"Public Transport\",\"89\":\"ATM\",\"90\":\"Public Transport\",\"91\":\"ATM\"},\"2nd Most Common Venue\":{\"0\":\"ATM\",\"1\":\"ATM\",\"2\":\"ATM\",\"3\":\"ATM\",\"4\":\"ATM\",\"5\":\"ATM\",\"6\":\"ATM\",\"7\":\"ATM\",\"8\":\"ATM\",\"9\":\"Public Transport\",\"10\":\"ATM\",\"11\":\"ATM\",\"12\":\"Public Transport\",\"13\":\"ATM\",\"14\":\"Public Transport\",\"15\":\"ATM\",\"16\":\"Public Transport\",\"17\":\"Public Transport\",\"18\":\"Public Transport\",\"19\":\"ATM\",\"20\":\"ATM\",\"21\":\"ATM\",\"22\":\"ATM\",\"23\":\"Supermarket\",\"24\":\"Public Transport\",\"25\":\"ATM\",\"26\":\"ATM\",\"27\":\"ATM\",\"28\":\"Public Transit Access\",\"29\":\"ATM\",\"30\":\"ATM\",\"31\":\"ATM\",\"32\":\"ATM\",\"33\":\"Supermarket\",\"34\":\"Public Transit Access\",\"35\":\"ATM\",\"36\":\"Public Transport\",\"37\":\"Supermarket\",\"38\":\"ATM\",\"39\":\"ATM\",\"40\":\"Supermarket\",\"41\":\"Supermarket\",\"42\":\"Public Transport\",\"43\":\"Supermarket\",\"44\":\"ATM\",\"45\":\"ATM\",\"46\":\"ATM\",\"47\":\"ATM\",\"48\":\"ATM\",\"49\":\"ATM\",\"50\":\"Public Transport\",\"51\":\"ATM\",\"52\":\"ATM\",\"53\":\"ATM\",\"54\":\"ATM\",\"55\":\"ATM\",\"56\":\"ATM\",\"57\":\"ATM\",\"58\":\"ATM\",\"59\":\"ATM\",\"60\":\"Public Transport\",\"61\":\"Public Transport\",\"62\":\"ATM\",\"63\":\"ATM\",\"64\":\"Public Transport\",\"65\":\"ATM\",\"66\":\"ATM\",\"67\":\"Public Transport\",\"68\":\"Public Transport\",\"69\":\"ATM\",\"70\":\"Supermarket\",\"71\":\"Supermarket\",\"72\":\"Supermarket\",\"73\":\"ATM\",\"74\":\"Supermarket\",\"75\":\"ATM\",\"76\":\"Public Transit Access\",\"77\":\"ATM\",\"78\":\"ATM\",\"79\":\"ATM\",\"80\":\"Public Transport\",\"81\":\"Supermarket\",\"82\":\"Supermarket\",\"83\":\"Public Transport\",\"84\":\"Public Transport\",\"85\":\"ATM\",\"86\":\"Supermarket\",\"87\":\"ATM\",\"88\":\"ATM\",\"89\":\"Public Transit Access\",\"90\":\"ATM\",\"91\":\"Casual Dining\"},\"3rd Most Common Venue\":{\"0\":\"Supermarket\",\"1\":\"Supermarket\",\"2\":\"Supermarket\",\"3\":\"Supermarket\",\"4\":\"Supermarket\",\"5\":\"Supermarket\",\"6\":\"Supermarket\",\"7\":\"Supermarket\",\"8\":\"Supermarket\",\"9\":\"Mall\",\"10\":\"Supermarket\",\"11\":\"Supermarket\",\"12\":\"Mall\",\"13\":\"Supermarket\",\"14\":\"Mall\",\"15\":\"Supermarket\",\"16\":\"Mall\",\"17\":\"Mall\",\"18\":\"Mall\",\"19\":\"Supermarket\",\"20\":\"Supermarket\",\"21\":\"Supermarket\",\"22\":\"Supermarket\",\"23\":\"Public Transport\",\"24\":\"Casual Dining\",\"25\":\"Supermarket\",\"26\":\"Supermarket\",\"27\":\"Supermarket\",\"28\":\"Public Transport\",\"29\":\"Supermarket\",\"30\":\"Supermarket\",\"31\":\"Supermarket\",\"32\":\"Supermarket\",\"33\":\"Public Transport\",\"34\":\"Public Transport\",\"35\":\"Supermarket\",\"36\":\"Mall\",\"37\":\"Public Transport\",\"38\":\"Supermarket\",\"39\":\"Supermarket\",\"40\":\"Public Transport\",\"41\":\"Public Transport\",\"42\":\"Mall\",\"43\":\"Public Transport\",\"44\":\"Supermarket\",\"45\":\"Supermarket\",\"46\":\"Supermarket\",\"47\":\"Supermarket\",\"48\":\"Supermarket\",\"49\":\"Supermarket\",\"50\":\"Mall\",\"51\":\"Supermarket\",\"52\":\"Supermarket\",\"53\":\"Supermarket\",\"54\":\"Supermarket\",\"55\":\"Supermarket\",\"56\":\"Supermarket\",\"57\":\"Supermarket\",\"58\":\"Supermarket\",\"59\":\"Supermarket\",\"60\":\"Mall\",\"61\":\"Mall\",\"62\":\"Supermarket\",\"63\":\"Supermarket\",\"64\":\"Mall\",\"65\":\"Supermarket\",\"66\":\"Supermarket\",\"67\":\"Casual Dining\",\"68\":\"Casual Dining\",\"69\":\"Supermarket\",\"70\":\"Public Transport\",\"71\":\"Public Transport\",\"72\":\"Public Transport\",\"73\":\"Supermarket\",\"74\":\"Public Transport\",\"75\":\"Supermarket\",\"76\":\"Public Transport\",\"77\":\"Supermarket\",\"78\":\"Supermarket\",\"79\":\"Supermarket\",\"80\":\"Mall\",\"81\":\"Public Transport\",\"82\":\"Public Transport\",\"83\":\"Mall\",\"84\":\"Mall\",\"85\":\"Supermarket\",\"86\":\"Public Transport\",\"87\":\"Supermarket\",\"88\":\"Supermarket\",\"89\":\"Public Transport\",\"90\":\"Supermarket\",\"91\":\"Mall\"},\"4th Most Common Venue\":{\"0\":\"Mall\",\"1\":\"Mall\",\"2\":\"Mall\",\"3\":\"Mall\",\"4\":\"Mall\",\"5\":\"Mall\",\"6\":\"Mall\",\"7\":\"Mall\",\"8\":\"Mall\",\"9\":\"Public Transit Access\",\"10\":\"Mall\",\"11\":\"Mall\",\"12\":\"Public Transit Access\",\"13\":\"Mall\",\"14\":\"Public Transit Access\",\"15\":\"Mall\",\"16\":\"Public Transit Access\",\"17\":\"Public Transit Access\",\"18\":\"Public Transit Access\",\"19\":\"Mall\",\"20\":\"Mall\",\"21\":\"Mall\",\"22\":\"Mall\",\"23\":\"Public Transit Access\",\"24\":\"Mall\",\"25\":\"Mall\",\"26\":\"Mall\",\"27\":\"Mall\",\"28\":\"Casual Dining\",\"29\":\"Mall\",\"30\":\"Mall\",\"31\":\"Mall\",\"32\":\"Mall\",\"33\":\"Public Transit Access\",\"34\":\"Casual Dining\",\"35\":\"Mall\",\"36\":\"Public Transit Access\",\"37\":\"Public Transit Access\",\"38\":\"Mall\",\"39\":\"Mall\",\"40\":\"Public Transit Access\",\"41\":\"Public Transit Access\",\"42\":\"Public Transit Access\",\"43\":\"Public Transit Access\",\"44\":\"Mall\",\"45\":\"Mall\",\"46\":\"Mall\",\"47\":\"Mall\",\"48\":\"Mall\",\"49\":\"Mall\",\"50\":\"Public Transit Access\",\"51\":\"Mall\",\"52\":\"Mall\",\"53\":\"Mall\",\"54\":\"Mall\",\"55\":\"Mall\",\"56\":\"Mall\",\"57\":\"Mall\",\"58\":\"Mall\",\"59\":\"Mall\",\"60\":\"Public Transit Access\",\"61\":\"Public Transit Access\",\"62\":\"Mall\",\"63\":\"Mall\",\"64\":\"Public Transit Access\",\"65\":\"Mall\",\"66\":\"Mall\",\"67\":\"Mall\",\"68\":\"Mall\",\"69\":\"Mall\",\"70\":\"Public Transit Access\",\"71\":\"Public Transit Access\",\"72\":\"Public Transit Access\",\"73\":\"Mall\",\"74\":\"Public Transit Access\",\"75\":\"Mall\",\"76\":\"Casual Dining\",\"77\":\"Mall\",\"78\":\"Mall\",\"79\":\"Mall\",\"80\":\"Public Transit Access\",\"81\":\"Public Transit Access\",\"82\":\"Public Transit Access\",\"83\":\"Public Transit Access\",\"84\":\"Public Transit Access\",\"85\":\"Mall\",\"86\":\"Public Transit Access\",\"87\":\"Mall\",\"88\":\"Mall\",\"89\":\"Casual Dining\",\"90\":\"Mall\",\"91\":\"Public Transit Access\"},\"5th Most Common Venue\":{\"0\":\"Public Transit Access\",\"1\":\"Public Transit Access\",\"2\":\"Public Transit Access\",\"3\":\"Public Transit Access\",\"4\":\"Public Transit Access\",\"5\":\"Public Transit Access\",\"6\":\"Public Transit Access\",\"7\":\"Public Transit Access\",\"8\":\"Public Transit Access\",\"9\":\"Supermarket\",\"10\":\"Public Transit Access\",\"11\":\"Public Transit Access\",\"12\":\"Supermarket\",\"13\":\"Public Transit Access\",\"14\":\"Supermarket\",\"15\":\"Public Transit Access\",\"16\":\"Supermarket\",\"17\":\"Supermarket\",\"18\":\"Supermarket\",\"19\":\"Public Transit Access\",\"20\":\"Public Transit Access\",\"21\":\"Public Transit Access\",\"22\":\"Public Transit Access\",\"23\":\"Casual Dining\",\"24\":\"Public Transit Access\",\"25\":\"Public Transit Access\",\"26\":\"Public Transit Access\",\"27\":\"Public Transit Access\",\"28\":\"Mall\",\"29\":\"Public Transit Access\",\"30\":\"Public Transit Access\",\"31\":\"Public Transit Access\",\"32\":\"Public Transit Access\",\"33\":\"Casual Dining\",\"34\":\"Mall\",\"35\":\"Public Transit Access\",\"36\":\"Supermarket\",\"37\":\"Casual Dining\",\"38\":\"Public Transit Access\",\"39\":\"Public Transit Access\",\"40\":\"Casual Dining\",\"41\":\"Casual Dining\",\"42\":\"Supermarket\",\"43\":\"Casual Dining\",\"44\":\"Public Transit Access\",\"45\":\"Public Transit Access\",\"46\":\"Public Transit Access\",\"47\":\"Public Transit Access\",\"48\":\"Public Transit Access\",\"49\":\"Public Transit Access\",\"50\":\"Supermarket\",\"51\":\"Public Transit Access\",\"52\":\"Public Transit Access\",\"53\":\"Public Transit Access\",\"54\":\"Public Transit Access\",\"55\":\"Public Transit Access\",\"56\":\"Public Transit Access\",\"57\":\"Public Transit Access\",\"58\":\"Public Transit Access\",\"59\":\"Public Transit Access\",\"60\":\"Supermarket\",\"61\":\"Supermarket\",\"62\":\"Public Transit Access\",\"63\":\"Public Transit Access\",\"64\":\"Supermarket\",\"65\":\"Public Transit Access\",\"66\":\"Public Transit Access\",\"67\":\"Public Transit Access\",\"68\":\"Public Transit Access\",\"69\":\"Public Transit Access\",\"70\":\"Casual Dining\",\"71\":\"Casual Dining\",\"72\":\"Casual Dining\",\"73\":\"Public Transit Access\",\"74\":\"Casual Dining\",\"75\":\"Public Transit Access\",\"76\":\"Mall\",\"77\":\"Public Transit Access\",\"78\":\"Public Transit Access\",\"79\":\"Public Transit Access\",\"80\":\"Supermarket\",\"81\":\"Casual Dining\",\"82\":\"Casual Dining\",\"83\":\"Supermarket\",\"84\":\"Supermarket\",\"85\":\"Public Transit Access\",\"86\":\"Casual Dining\",\"87\":\"Public Transit Access\",\"88\":\"Public Transit Access\",\"89\":\"Mall\",\"90\":\"Public Transit Access\",\"91\":\"Public Transport\"}}", "{\"Category\":{\"0\":\"Public Transport\",\"1\":\"Public Transport\",\"2\":\"Public Transport\",\"3\":\"Supermarket\",\"4\":\"Supermarket\",\"5\":\"Supermarket\",\"6\":\"Supermarket\",\"7\":\"Supermarket\",\"8\":\"Supermarket\",\"9\":\"Supermarket\",\"10\":\"Supermarket\",\"11\":\"Supermarket\",\"12\":\"Supermarket\",\"13\":\"Supermarket\",\"14\":\"Supermarket\",\"15\":\"Supermarket\",\"16\":\"Supermarket\",\"17\":\"Supermarket\",\"18\":\"Supermarket\",\"19\":\"Supermarket\",\"20\":\"Supermarket\"},\"City\":{\"0\":\"Vancouver\",\"1\":\"Vancouver\",\"2\":\"Vancouver\",\"3\":\"Vancouver\",\"4\":\"Vancouver\",\"5\":\"Vancouver\",\"6\":\"Vancouver\",\"7\":\"Vancouver\",\"8\":\"Vancouver\",\"9\":\"Vancouver\",\"10\":\"Vancouver\",\"11\":\"Vancouver\",\"12\":\"Vancouver\",\"13\":\"Vancouver\",\"14\":\"Vancouver\",\"15\":\"Vancouver\",\"16\":\"Vancouver\",\"17\":\"Vancouver\",\"18\":\"Vancouver\",\"19\":\"Vancouver\",\"20\":\"Vancouver\"},\"Neighborhood\":{\"0\":\"Richards Street\",\"1\":\"Chinatown\",\"2\":\"West End\",\"3\":\"Richards Street\",\"4\":\"Hornby Street\",\"5\":\"Richards Street\",\"6\":\"West End\",\"7\":\"West End\",\"8\":\"Richards Street\",\"9\":\"East Cordova Street\",\"10\":\"Melville Street\",\"11\":\"Alberni Street\",\"12\":\"West End\",\"13\":\"Canada Place\",\"14\":\"Coal Harbour\",\"15\":\"Chinatown\",\"16\":\"Chinatown\",\"17\":\"Drake Street\",\"18\":\"Comox Street\",\"19\":\"Chinatown\",\"20\":\"Chinatown\"},\"Cluster Labels\":{\"0\":3,\"1\":3,\"2\":3,\"3\":3,\"4\":3,\"5\":3,\"6\":3,\"7\":3,\"8\":3,\"9\":3,\"10\":3,\"11\":3,\"12\":3,\"13\":3,\"14\":3,\"15\":3,\"16\":3,\"17\":3,\"18\":3,\"19\":3,\"20\":3},\"1st Most Common Venue\":{\"0\":\"Supermarket\",\"1\":\"Supermarket\",\"2\":\"Supermarket\",\"3\":\"Supermarket\",\"4\":\"Supermarket\",\"5\":\"Supermarket\",\"6\":\"Supermarket\",\"7\":\"Supermarket\",\"8\":\"Supermarket\",\"9\":\"Supermarket\",\"10\":\"Supermarket\",\"11\":\"Supermarket\",\"12\":\"Supermarket\",\"13\":\"Supermarket\",\"14\":\"Supermarket\",\"15\":\"Supermarket\",\"16\":\"Supermarket\",\"17\":\"Supermarket\",\"18\":\"Supermarket\",\"19\":\"Supermarket\",\"20\":\"Supermarket\"},\"2nd Most Common Venue\":{\"0\":\"Public Transport\",\"1\":\"Public Transport\",\"2\":\"Public Transport\",\"3\":\"Public Transport\",\"4\":\"ATM\",\"5\":\"Public Transport\",\"6\":\"Public Transport\",\"7\":\"Public Transport\",\"8\":\"Public Transport\",\"9\":\"ATM\",\"10\":\"ATM\",\"11\":\"ATM\",\"12\":\"Public Transport\",\"13\":\"ATM\",\"14\":\"ATM\",\"15\":\"Public Transport\",\"16\":\"Public Transport\",\"17\":\"ATM\",\"18\":\"ATM\",\"19\":\"Public Transport\",\"20\":\"Public Transport\"},\"3rd Most Common Venue\":{\"0\":\"ATM\",\"1\":\"ATM\",\"2\":\"ATM\",\"3\":\"ATM\",\"4\":\"Casual Dining\",\"5\":\"ATM\",\"6\":\"ATM\",\"7\":\"ATM\",\"8\":\"ATM\",\"9\":\"Casual Dining\",\"10\":\"Casual Dining\",\"11\":\"Casual Dining\",\"12\":\"ATM\",\"13\":\"Casual Dining\",\"14\":\"Casual Dining\",\"15\":\"ATM\",\"16\":\"ATM\",\"17\":\"Casual Dining\",\"18\":\"Casual Dining\",\"19\":\"ATM\",\"20\":\"ATM\"},\"4th Most Common Venue\":{\"0\":\"Casual Dining\",\"1\":\"Casual Dining\",\"2\":\"Casual Dining\",\"3\":\"Casual Dining\",\"4\":\"Mall\",\"5\":\"Casual Dining\",\"6\":\"Casual Dining\",\"7\":\"Casual Dining\",\"8\":\"Casual Dining\",\"9\":\"Mall\",\"10\":\"Mall\",\"11\":\"Mall\",\"12\":\"Casual Dining\",\"13\":\"Mall\",\"14\":\"Mall\",\"15\":\"Casual Dining\",\"16\":\"Casual Dining\",\"17\":\"Mall\",\"18\":\"Mall\",\"19\":\"Casual Dining\",\"20\":\"Casual Dining\"},\"5th Most Common Venue\":{\"0\":\"Mall\",\"1\":\"Mall\",\"2\":\"Mall\",\"3\":\"Mall\",\"4\":\"Public Transit Access\",\"5\":\"Mall\",\"6\":\"Mall\",\"7\":\"Mall\",\"8\":\"Mall\",\"9\":\"Public Transit Access\",\"10\":\"Public Transit Access\",\"11\":\"Public Transit Access\",\"12\":\"Mall\",\"13\":\"Public Transit Access\",\"14\":\"Public Transit Access\",\"15\":\"Mall\",\"16\":\"Mall\",\"17\":\"Public Transit Access\",\"18\":\"Public Transit Access\",\"19\":\"Mall\",\"20\":\"Mall\"}}", "{\"Category\":{\"0\":\"Public Transport\",\"1\":\"Public Transport\",\"2\":\"Public Transport\",\"3\":\"Public Transport\",\"4\":\"Public Transport\",\"5\":\"Public Transport\",\"6\":\"Public Transport\",\"7\":\"Public Transport\",\"8\":\"Public Transport\",\"9\":\"Public Transport\",\"10\":\"Public Transport\",\"11\":\"Public Transport\",\"12\":\"Public Transport\",\"13\":\"Public Transport\",\"14\":\"Public Transport\",\"15\":\"Public Transport\",\"16\":\"Public Transport\",\"17\":\"Public Transport\",\"18\":\"Public Transport\",\"19\":\"Public Transport\",\"20\":\"Public Transport\",\"21\":\"Public Transport\",\"22\":\"Public Transport\",\"23\":\"Public Transport\",\"24\":\"Public Transport\",\"25\":\"Public Transport\",\"26\":\"Public Transport\",\"27\":\"Public Transport\",\"28\":\"Public Transport\",\"29\":\"Public Transport\",\"30\":\"Public Transport\",\"31\":\"Public Transport\",\"32\":\"Public Transport\",\"33\":\"Public Transport\",\"34\":\"Supermarket\",\"35\":\"Supermarket\",\"36\":\"Supermarket\",\"37\":\"Supermarket\",\"38\":\"Supermarket\",\"39\":\"Supermarket\",\"40\":\"Supermarket\",\"41\":\"Supermarket\",\"42\":\"Supermarket\",\"43\":\"Supermarket\",\"44\":\"Supermarket\",\"45\":\"Supermarket\",\"46\":\"Supermarket\",\"47\":\"Supermarket\",\"48\":\"Supermarket\",\"49\":\"Supermarket\",\"50\":\"Supermarket\",\"51\":\"Supermarket\",\"52\":\"Casual Dining\",\"53\":\"Supermarket\",\"54\":\"Supermarket\",\"55\":\"Supermarket\",\"56\":\"Supermarket\",\"57\":\"Supermarket\",\"58\":\"Supermarket\",\"59\":\"Mall\",\"60\":\"Mall\",\"61\":\"Mall\",\"62\":\"ATM\",\"63\":\"ATM\",\"64\":\"ATM\"},\"City\":{\"0\":\"Vancouver\",\"1\":\"Vancouver\",\"2\":\"Vancouver\",\"3\":\"Vancouver\",\"4\":\"Vancouver\",\"5\":\"Vancouver\",\"6\":\"Vancouver\",\"7\":\"Vancouver\",\"8\":\"Vancouver\",\"9\":\"Vancouver\",\"10\":\"Vancouver\",\"11\":\"Vancouver\",\"12\":\"Vancouver\",\"13\":\"Vancouver\",\"14\":\"Vancouver\",\"15\":\"Vancouver\",\"16\":\"Vancouver\",\"17\":\"Vancouver\",\"18\":\"Vancouver\",\"19\":\"Vancouver\",\"20\":\"Vancouver\",\"21\":\"Vancouver\",\"22\":\"Vancouver\",\"23\":\"Vancouver\",\"24\":\"Vancouver\",\"25\":\"Vancouver\",\"26\":\"Vancouver\",\"27\":\"Vancouver\",\"28\":\"Vancouver\",\"29\":\"Vancouver\",\"30\":\"Vancouver\",\"31\":\"Vancouver\",\"32\":\"Vancouver\",\"33\":\"Vancouver\",\"34\":\"Vancouver\",\"35\":\"Vancouver\",\"36\":\"Vancouver\",\"37\":\"Vancouver\",\"38\":\"Vancouver\",\"39\":\"Vancouver\",\"40\":\"Vancouver\",\"41\":\"Vancouver\",\"42\":\"Vancouver\",\"43\":\"Vancouver\",\"44\":\"Vancouver\",\"45\":\"Vancouver\",\"46\":\"Vancouver\",\"47\":\"Vancouver\",\"48\":\"Vancouver\",\"49\":\"Vancouver\",\"50\":\"Vancouver\",\"51\":\"Vancouver\",\"52\":\"Vancouver\",\"53\":\"Vancouver\",\"54\":\"Vancouver\",\"55\":\"Vancouver\",\"56\":\"Vancouver\",\"57\":\"Vancouver\",\"58\":\"Vancouver\",\"59\":\"Vancouver\",\"60\":\"Vancouver\",\"61\":\"Vancouver\",\"62\":\"Vancouver\",\"63\":\"Vancouver\",\"64\":\"Vancouver\"},\"Neighborhood\":{\"0\":\"Granville Street\",\"1\":\"Howe Street\",\"2\":\"Gastown\",\"3\":\"Granville Street\",\"4\":\"Hamilton Street\",\"5\":\"Granville Street\",\"6\":\"Granville Street\",\"7\":\"Granville Street\",\"8\":\"Granville Street\",\"9\":\"West Hastings Street\",\"10\":\"West Hastings Street\",\"11\":\"Gastown\",\"12\":\"Gastown\",\"13\":\"West Hastings Street\",\"14\":\"West Hastings Street\",\"15\":\"West Hastings Street\",\"16\":\"West Hastings Street\",\"17\":\"Gastown\",\"18\":\"Gastown\",\"19\":\"West Hastings Street\",\"20\":\"West Hastings Street\",\"21\":\"Gastown\",\"22\":\"Gastown\",\"23\":\"Abbott Street\",\"24\":\"Abbott Street\",\"25\":\"Gastown\",\"26\":\"Gastown\",\"27\":\"Gastown\",\"28\":\"Gastown\",\"29\":\"Water Street\",\"30\":\"Gastown\",\"31\":\"Granville Street\",\"32\":\"Hamilton Street\",\"33\":\"Hamilton Street\",\"34\":\"Hamilton Street\",\"35\":\"Hamilton Street\",\"36\":\"Granville Street\",\"37\":\"Gastown\",\"38\":\"West Hastings Street\",\"39\":\"Granville Street\",\"40\":\"West Hastings Street\",\"41\":\"West Hastings Street\",\"42\":\"Gastown\",\"43\":\"Gastown\",\"44\":\"West Hastings Street\",\"45\":\"West Hastings Street\",\"46\":\"Howe Street\",\"47\":\"Abbott Street\",\"48\":\"Abbott Street\",\"49\":\"Gastown\",\"50\":\"Gastown\",\"51\":\"Gastown\",\"52\":\"Gastown\",\"53\":\"Gastown\",\"54\":\"Gastown\",\"55\":\"Gastown\",\"56\":\"Gastown\",\"57\":\"Granville Street\",\"58\":\"Gastown\",\"59\":\"Granville Street\",\"60\":\"West Hastings Street\",\"61\":\"Water Street\",\"62\":\"West Hastings Street\",\"63\":\"West Hastings Street\",\"64\":\"West Hastings Street\"},\"Cluster Labels\":{\"0\":4,\"1\":4,\"2\":4,\"3\":4,\"4\":4,\"5\":4,\"6\":4,\"7\":4,\"8\":4,\"9\":4,\"10\":4,\"11\":4,\"12\":4,\"13\":4,\"14\":4,\"15\":4,\"16\":4,\"17\":4,\"18\":4,\"19\":4,\"20\":4,\"21\":4,\"22\":4,\"23\":4,\"24\":4,\"25\":4,\"26\":4,\"27\":4,\"28\":4,\"29\":4,\"30\":4,\"31\":4,\"32\":4,\"33\":4,\"34\":4,\"35\":4,\"36\":4,\"37\":4,\"38\":4,\"39\":4,\"40\":4,\"41\":4,\"42\":4,\"43\":4,\"44\":4,\"45\":4,\"46\":4,\"47\":4,\"48\":4,\"49\":4,\"50\":4,\"51\":4,\"52\":4,\"53\":4,\"54\":4,\"55\":4,\"56\":4,\"57\":4,\"58\":4,\"59\":4,\"60\":4,\"61\":4,\"62\":4,\"63\":4,\"64\":4},\"1st Most Common Venue\":{\"0\":\"Public Transport\",\"1\":\"Public Transport\",\"2\":\"Public Transport\",\"3\":\"Public Transport\",\"4\":\"Public Transport\",\"5\":\"Public Transport\",\"6\":\"Public Transport\",\"7\":\"Public Transport\",\"8\":\"Public Transport\",\"9\":\"Public Transport\",\"10\":\"Public Transport\",\"11\":\"Public Transport\",\"12\":\"Public Transport\",\"13\":\"Public Transport\",\"14\":\"Public Transport\",\"15\":\"Public Transport\",\"16\":\"Public Transport\",\"17\":\"Public Transport\",\"18\":\"Public Transport\",\"19\":\"Public Transport\",\"20\":\"Public Transport\",\"21\":\"Public Transport\",\"22\":\"Public Transport\",\"23\":\"Public Transport\",\"24\":\"Public Transport\",\"25\":\"Public Transport\",\"26\":\"Public Transport\",\"27\":\"Public Transport\",\"28\":\"Public Transport\",\"29\":\"Mall\",\"30\":\"Public Transport\",\"31\":\"Public Transport\",\"32\":\"Public Transport\",\"33\":\"Public Transport\",\"34\":\"Public Transport\",\"35\":\"Public Transport\",\"36\":\"Public Transport\",\"37\":\"Public Transport\",\"38\":\"Public Transport\",\"39\":\"Public Transport\",\"40\":\"Public Transport\",\"41\":\"Public Transport\",\"42\":\"Public Transport\",\"43\":\"Public Transport\",\"44\":\"Public Transport\",\"45\":\"Public Transport\",\"46\":\"Public Transport\",\"47\":\"Public Transport\",\"48\":\"Public Transport\",\"49\":\"Public Transport\",\"50\":\"Public Transport\",\"51\":\"Public Transport\",\"52\":\"Public Transport\",\"53\":\"Public Transport\",\"54\":\"Public Transport\",\"55\":\"Public Transport\",\"56\":\"Public Transport\",\"57\":\"Public Transport\",\"58\":\"Public Transport\",\"59\":\"Public Transport\",\"60\":\"Public Transport\",\"61\":\"Mall\",\"62\":\"Public Transport\",\"63\":\"Public Transport\",\"64\":\"Public Transport\"},\"2nd Most Common Venue\":{\"0\":\"Supermarket\",\"1\":\"Supermarket\",\"2\":\"Supermarket\",\"3\":\"Supermarket\",\"4\":\"Supermarket\",\"5\":\"Supermarket\",\"6\":\"Supermarket\",\"7\":\"Supermarket\",\"8\":\"Supermarket\",\"9\":\"Supermarket\",\"10\":\"Supermarket\",\"11\":\"Supermarket\",\"12\":\"Supermarket\",\"13\":\"Supermarket\",\"14\":\"Supermarket\",\"15\":\"Supermarket\",\"16\":\"Supermarket\",\"17\":\"Supermarket\",\"18\":\"Supermarket\",\"19\":\"Supermarket\",\"20\":\"Supermarket\",\"21\":\"Supermarket\",\"22\":\"Supermarket\",\"23\":\"Supermarket\",\"24\":\"Supermarket\",\"25\":\"Supermarket\",\"26\":\"Supermarket\",\"27\":\"Supermarket\",\"28\":\"Supermarket\",\"29\":\"Public Transport\",\"30\":\"Supermarket\",\"31\":\"Supermarket\",\"32\":\"Supermarket\",\"33\":\"Supermarket\",\"34\":\"Supermarket\",\"35\":\"Supermarket\",\"36\":\"Supermarket\",\"37\":\"Supermarket\",\"38\":\"Supermarket\",\"39\":\"Supermarket\",\"40\":\"Supermarket\",\"41\":\"Supermarket\",\"42\":\"Supermarket\",\"43\":\"Supermarket\",\"44\":\"Supermarket\",\"45\":\"Supermarket\",\"46\":\"Supermarket\",\"47\":\"Supermarket\",\"48\":\"Supermarket\",\"49\":\"Supermarket\",\"50\":\"Supermarket\",\"51\":\"Supermarket\",\"52\":\"Supermarket\",\"53\":\"Supermarket\",\"54\":\"Supermarket\",\"55\":\"Supermarket\",\"56\":\"Supermarket\",\"57\":\"Supermarket\",\"58\":\"Supermarket\",\"59\":\"Supermarket\",\"60\":\"Supermarket\",\"61\":\"Public Transport\",\"62\":\"Supermarket\",\"63\":\"Supermarket\",\"64\":\"Supermarket\"},\"3rd Most Common Venue\":{\"0\":\"Mall\",\"1\":\"ATM\",\"2\":\"Casual Dining\",\"3\":\"Mall\",\"4\":\"ATM\",\"5\":\"Mall\",\"6\":\"Mall\",\"7\":\"Mall\",\"8\":\"Mall\",\"9\":\"ATM\",\"10\":\"ATM\",\"11\":\"Casual Dining\",\"12\":\"Casual Dining\",\"13\":\"ATM\",\"14\":\"ATM\",\"15\":\"ATM\",\"16\":\"ATM\",\"17\":\"Casual Dining\",\"18\":\"Casual Dining\",\"19\":\"ATM\",\"20\":\"ATM\",\"21\":\"Casual Dining\",\"22\":\"Casual Dining\",\"23\":\"ATM\",\"24\":\"ATM\",\"25\":\"Casual Dining\",\"26\":\"Casual Dining\",\"27\":\"Casual Dining\",\"28\":\"Casual Dining\",\"29\":\"ATM\",\"30\":\"Casual Dining\",\"31\":\"Mall\",\"32\":\"ATM\",\"33\":\"ATM\",\"34\":\"ATM\",\"35\":\"ATM\",\"36\":\"Mall\",\"37\":\"Casual Dining\",\"38\":\"ATM\",\"39\":\"Mall\",\"40\":\"ATM\",\"41\":\"ATM\",\"42\":\"Casual Dining\",\"43\":\"Casual Dining\",\"44\":\"ATM\",\"45\":\"ATM\",\"46\":\"ATM\",\"47\":\"ATM\",\"48\":\"ATM\",\"49\":\"Casual Dining\",\"50\":\"Casual Dining\",\"51\":\"Casual Dining\",\"52\":\"Casual Dining\",\"53\":\"Casual Dining\",\"54\":\"Casual Dining\",\"55\":\"Casual Dining\",\"56\":\"Casual Dining\",\"57\":\"Mall\",\"58\":\"Casual Dining\",\"59\":\"Mall\",\"60\":\"ATM\",\"61\":\"ATM\",\"62\":\"ATM\",\"63\":\"ATM\",\"64\":\"ATM\"},\"4th Most Common Venue\":{\"0\":\"ATM\",\"1\":\"Casual Dining\",\"2\":\"ATM\",\"3\":\"ATM\",\"4\":\"Casual Dining\",\"5\":\"ATM\",\"6\":\"ATM\",\"7\":\"ATM\",\"8\":\"ATM\",\"9\":\"Mall\",\"10\":\"Mall\",\"11\":\"ATM\",\"12\":\"ATM\",\"13\":\"Mall\",\"14\":\"Mall\",\"15\":\"Mall\",\"16\":\"Mall\",\"17\":\"ATM\",\"18\":\"ATM\",\"19\":\"Mall\",\"20\":\"Mall\",\"21\":\"ATM\",\"22\":\"ATM\",\"23\":\"Casual Dining\",\"24\":\"Casual Dining\",\"25\":\"ATM\",\"26\":\"ATM\",\"27\":\"ATM\",\"28\":\"ATM\",\"29\":\"Casual Dining\",\"30\":\"ATM\",\"31\":\"ATM\",\"32\":\"Casual Dining\",\"33\":\"Casual Dining\",\"34\":\"Casual Dining\",\"35\":\"Casual Dining\",\"36\":\"ATM\",\"37\":\"ATM\",\"38\":\"Mall\",\"39\":\"ATM\",\"40\":\"Mall\",\"41\":\"Mall\",\"42\":\"ATM\",\"43\":\"ATM\",\"44\":\"Mall\",\"45\":\"Mall\",\"46\":\"Casual Dining\",\"47\":\"Casual Dining\",\"48\":\"Casual Dining\",\"49\":\"ATM\",\"50\":\"ATM\",\"51\":\"ATM\",\"52\":\"ATM\",\"53\":\"ATM\",\"54\":\"ATM\",\"55\":\"ATM\",\"56\":\"ATM\",\"57\":\"ATM\",\"58\":\"ATM\",\"59\":\"ATM\",\"60\":\"Mall\",\"61\":\"Casual Dining\",\"62\":\"Mall\",\"63\":\"Mall\",\"64\":\"Mall\"},\"5th Most Common Venue\":{\"0\":\"Casual Dining\",\"1\":\"Mall\",\"2\":\"Mall\",\"3\":\"Casual Dining\",\"4\":\"Mall\",\"5\":\"Casual Dining\",\"6\":\"Casual Dining\",\"7\":\"Casual Dining\",\"8\":\"Casual Dining\",\"9\":\"Casual Dining\",\"10\":\"Casual Dining\",\"11\":\"Mall\",\"12\":\"Mall\",\"13\":\"Casual Dining\",\"14\":\"Casual Dining\",\"15\":\"Casual Dining\",\"16\":\"Casual Dining\",\"17\":\"Mall\",\"18\":\"Mall\",\"19\":\"Casual Dining\",\"20\":\"Casual Dining\",\"21\":\"Mall\",\"22\":\"Mall\",\"23\":\"Mall\",\"24\":\"Mall\",\"25\":\"Mall\",\"26\":\"Mall\",\"27\":\"Mall\",\"28\":\"Mall\",\"29\":\"Public Transit Access\",\"30\":\"Mall\",\"31\":\"Casual Dining\",\"32\":\"Mall\",\"33\":\"Mall\",\"34\":\"Mall\",\"35\":\"Mall\",\"36\":\"Casual Dining\",\"37\":\"Mall\",\"38\":\"Casual Dining\",\"39\":\"Casual Dining\",\"40\":\"Casual Dining\",\"41\":\"Casual Dining\",\"42\":\"Mall\",\"43\":\"Mall\",\"44\":\"Casual Dining\",\"45\":\"Casual Dining\",\"46\":\"Mall\",\"47\":\"Mall\",\"48\":\"Mall\",\"49\":\"Mall\",\"50\":\"Mall\",\"51\":\"Mall\",\"52\":\"Mall\",\"53\":\"Mall\",\"54\":\"Mall\",\"55\":\"Mall\",\"56\":\"Mall\",\"57\":\"Casual Dining\",\"58\":\"Mall\",\"59\":\"Casual Dining\",\"60\":\"Casual Dining\",\"61\":\"Public Transit Access\",\"62\":\"Casual Dining\",\"63\":\"Casual Dining\",\"64\":\"Casual Dining\"}}"]}